modernblaseball/__init__.py
modernblaseball/modern_blaseball.py
modernblaseball-0.5.6.dist-info/LICENSE.md
modernblaseball-0.5.6.dist-info/METADATA
modernblaseball-0.5.6.dist-info/WHEEL
modernblaseball-0.5.6.dist-info/top_level.txt
modernblaseball-0.5.6.dist-info/RECORD
