Metadata-Version: 2.1
Name: modernblaseball
Version: 0.5.6
Summary: An interface for the blaseball API
Home-page: https://github.com/helloimowen/modern-blaseball
Author: Owen Sanders
Author-email: helloimowens@gmail.com
License: UNKNOWN
Platform: UNKNOWN
Classifier: Programming Language :: Python :: 3
Classifier: License :: OSI Approved :: MIT License
Classifier: Operating System :: OS Independent
Requires-Python: >=3.6
